rstms_tq/__init__.py
rstms_tq/__main__.py
rstms_tq/tq.py
rstms_tq/version.py
rstms_tq-0.1.11.dist-info/entry_points.txt
rstms_tq-0.1.11.dist-info/LICENSE
rstms_tq-0.1.11.dist-info/WHEEL
rstms_tq-0.1.11.dist-info/METADATA
rstms_tq-0.1.11.dist-info/RECORD
